README.rst
flask_datadog.py
setup.py
Flask_Datadog.egg-info/PKG-INFO
Flask_Datadog.egg-info/SOURCES.txt
Flask_Datadog.egg-info/dependency_links.txt
Flask_Datadog.egg-info/not-zip-safe
Flask_Datadog.egg-info/requires.txt
Flask_Datadog.egg-info/top_level.txt