Metadata-Version: 1.1
Name: Flask-Datadog
Version: 0.1.2
Summary: Access to dogstatsd in your app.
Home-page: https://github.com/50onRed/flask-datadog.git
Author: 50onRed
Author-email: marcus.mccurdy@gmail.com
License: BSD
Platform: any
Classifier: Environment :: Web Environment
Classifier: Intended Audience :: Developers
Classifier: License :: OSI Approved :: BSD License
Classifier: Operating System :: OS Independent
Classifier: Programming Language :: Python
Classifier: Topic :: Software Development :: Libraries :: Python Modules
